{
  "metadata": {
    "source": "reddit",
    "fetched_at": "2026-02-02T19:43:31.321689+00:00",
    "post_count": 14,
    "subreddits": [
      ""
    ]
  },
  "posts": [
    {
      "id": "YQUwbBF0wz0",
      "title": "2 FREE Tools To Spy On Any Competitor | Traffic, Sales, Ads",
      "url": "https://www.youtube.com/watch?v=YQUwbBF0wz0",
      "thumbnail_url": "https://img.youtube.com/vi/YQUwbBF0wz0/hqdefault.jpg",
      "views": 20822,
      "like_count": 1938,
      "comment_count": 9,
      "channel_name": "D2C Decoded By Nikhil",
      "channel_id": "UC82bPBmx-R4ntQoGwat_mow",
      "channel_avg_views": 3488.44,
      "outlier_score": 11.14,
      "recency_boost": 1.24,
      "engagement_modifiers": 1.5,
      "published_at": "2026-02-01T12:30:00Z",
      "fetched_at": "2026-02-02T19:42:50.294156+00:00",
      "source": "youtube",
      "api_source": "youtube_data_api"
    },
    {
      "id": "Gvjw4L6qZ30",
      "title": "I Automated My Dropshipping Business in 8 Minutes (2026 Strategy)",
      "url": "https://www.youtube.com/watch?v=Gvjw4L6qZ30",
      "thumbnail_url": "https://img.youtube.com/vi/Gvjw4L6qZ30/hqdefault.jpg",
      "views": 16789,
      "like_count": 31,
      "comment_count": 5,
      "channel_name": "James Pelton",
      "channel_id": "UCN_RnjVd-kKDr2xaasirPmw",
      "channel_avg_views": 3102.64,
      "outlier_score": 8.12,
      "recency_boost": 1.0,
      "engagement_modifiers": 1.5,
      "published_at": "2026-01-19T21:09:21Z",
      "fetched_at": "2026-02-02T19:42:20.532640+00:00",
      "source": "youtube",
      "api_source": "youtube_data_api"
    },
    {
      "id": "P967C9nwb9o",
      "title": "How to Auto-Ungate 100 Brands in 15 Minutes (NEW AMAZON UNGATING METHOD)",
      "url": "https://www.youtube.com/watch?v=P967C9nwb9o",
      "thumbnail_url": "https://img.youtube.com/vi/P967C9nwb9o/hqdefault.jpg",
      "views": 4202,
      "like_count": 186,
      "comment_count": 54,
      "channel_name": "Fields of Profit",
      "channel_id": "UCFPLwQH8B5avF9pJ1v76dZg",
      "channel_avg_views": 939.42,
      "outlier_score": 6.71,
      "recency_boost": 1.0,
      "engagement_modifiers": 1.5,
      "published_at": "2026-01-26T18:49:32Z",
      "fetched_at": "2026-02-02T19:42:58.791506+00:00",
      "source": "youtube",
      "api_source": "youtube_data_api"
    },
    {
      "id": "WbJzB4KVVd4",
      "title": "$250M CEO Explains How to Build A Brand in 2026",
      "url": "https://www.youtube.com/watch?v=WbJzB4KVVd4",
      "thumbnail_url": "https://img.youtube.com/vi/WbJzB4KVVd4/hqdefault.jpg",
      "views": 22275,
      "like_count": 781,
      "comment_count": 30,
      "channel_name": "Hormozi Highlights",
      "channel_id": "UCrvchO1h6lWZAuGaa1LqX9Q",
      "channel_avg_views": 7626.38,
      "outlier_score": 4.63,
      "recency_boost": 1.06,
      "engagement_modifiers": 1.5,
      "published_at": "2026-01-28T02:55:33Z",
      "fetched_at": "2026-02-02T19:42:41.724690+00:00",
      "source": "youtube",
      "api_source": "youtube_data_api"
    },
    {
      "id": "FuaJV8vk7QM",
      "title": "Get an Inside Look at the Direct-to-Consumer Brand Quince",
      "url": "https://www.youtube.com/watch?v=FuaJV8vk7QM",
      "thumbnail_url": "https://img.youtube.com/vi/FuaJV8vk7QM/hqdefault.jpg",
      "views": 55605,
      "like_count": 537,
      "comment_count": 39,
      "channel_name": "TODAY",
      "channel_id": "UChDKyKQ59fYz3JO2fl0Z6sg",
      "channel_avg_views": 16379.28,
      "outlier_score": 4.41,
      "recency_boost": 1.0,
      "engagement_modifiers": 1.3,
      "published_at": "2026-01-21T17:15:00Z",
      "fetched_at": "2026-02-02T19:42:49.063705+00:00",
      "source": "youtube",
      "api_source": "youtube_data_api"
    },
    {
      "id": "ZEMnUJIgtLA",
      "title": "Beginners Guide to Amazon FBA in 2026 (8+ Hours)",
      "url": "https://www.youtube.com/watch?v=ZEMnUJIgtLA",
      "thumbnail_url": "https://img.youtube.com/vi/ZEMnUJIgtLA/hqdefault.jpg",
      "views": 6632,
      "like_count": 300,
      "comment_count": 80,
      "channel_name": "Flips4Miles",
      "channel_id": "UCd0gngaeuOlUQr8K5SEVgcA",
      "channel_avg_views": 2051.42,
      "outlier_score": 4.2,
      "recency_boost": 1.0,
      "engagement_modifiers": 1.3,
      "published_at": "2026-01-21T12:26:18Z",
      "fetched_at": "2026-02-02T19:42:56.751829+00:00",
      "source": "youtube",
      "api_source": "youtube_data_api"
    },
    {
      "id": "9LwMK4qU5XI",
      "title": "El Secreto para GANAR DINERO con un Negocio por Internet en AMAZON FBA: Caso REAL $65,000/mes",
      "url": "https://www.youtube.com/watch?v=9LwMK4qU5XI",
      "thumbnail_url": "https://img.youtube.com/vi/9LwMK4qU5XI/hqdefault.jpg",
      "views": 11334,
      "like_count": 460,
      "comment_count": 39,
      "channel_name": "Actitud Millonaria - Josue Peña",
      "channel_id": "UCdRuuenOZ4zoVwT-IJsRMTA",
      "channel_avg_views": 4237.92,
      "outlier_score": 4.01,
      "recency_boost": 1.0,
      "engagement_modifiers": 1.5,
      "published_at": "2026-01-19T21:00:09Z",
      "fetched_at": "2026-02-02T19:42:57.884247+00:00",
      "source": "youtube",
      "api_source": "youtube_data_api"
    },
    {
      "id": "nJ65s9NGlCE",
      "title": "I BLEW UP an AI Dropshipping Store in 30 Days (RAW Results)",
      "url": "https://www.youtube.com/watch?v=nJ65s9NGlCE",
      "thumbnail_url": "https://img.youtube.com/vi/nJ65s9NGlCE/hqdefault.jpg",
      "views": 16955,
      "like_count": 775,
      "comment_count": 78,
      "channel_name": "Ac Hampton",
      "channel_id": "UC3qB4xFJkl0EYoTVbhnn0OQ",
      "channel_avg_views": 6822.42,
      "outlier_score": 3.73,
      "recency_boost": 1.0,
      "engagement_modifiers": 1.5,
      "published_at": "2026-01-26T13:01:26Z",
      "fetched_at": "2026-02-02T19:42:34.578045+00:00",
      "source": "youtube",
      "api_source": "youtube_data_api"
    },
    {
      "id": "Ew0F9lcp_U4",
      "title": "Cómo Vender en Amazon FBA en 2026",
      "url": "https://www.youtube.com/watch?v=Ew0F9lcp_U4",
      "thumbnail_url": "https://img.youtube.com/vi/Ew0F9lcp_U4/hqdefault.jpg",
      "views": 5298,
      "like_count": 95,
      "comment_count": 18,
      "channel_name": "Rod Hilfer",
      "channel_id": "UCVg0cNyIFR2WACpNN6J9aFA",
      "channel_avg_views": 1769.1,
      "outlier_score": 2.99,
      "recency_boost": 1.0,
      "engagement_modifiers": 1.0,
      "published_at": "2026-01-20T13:00:27Z",
      "fetched_at": "2026-02-02T19:42:59.282143+00:00",
      "source": "youtube",
      "api_source": "youtube_data_api"
    },
    {
      "id": "K7wkJ55J9b0",
      "title": "I Built a Full Print on Demand Store in 10 Minutes (No Shopify)",
      "url": "https://www.youtube.com/watch?v=K7wkJ55J9b0",
      "thumbnail_url": "https://img.youtube.com/vi/K7wkJ55J9b0/hqdefault.jpg",
      "views": 4639,
      "like_count": 211,
      "comment_count": 23,
      "channel_name": "Ryan Hogue Passive Income",
      "channel_id": "UChd9BBD7NWmkbwhsmV2-XoA",
      "channel_avg_views": 2717.6,
      "outlier_score": 2.77,
      "recency_boost": 1.08,
      "engagement_modifiers": 1.5,
      "published_at": "2026-01-28T17:26:23Z",
      "fetched_at": "2026-02-02T19:42:37.572893+00:00",
      "source": "youtube",
      "api_source": "youtube_data_api"
    },
    {
      "id": "z60aMlXEbRM",
      "title": "How to Hire (or Create) Elite Creative Strategists for DTC Brands | Meta Ads & Creative Strategy",
      "url": "https://www.youtube.com/watch?v=z60aMlXEbRM",
      "thumbnail_url": "https://img.youtube.com/vi/z60aMlXEbRM/hqdefault.jpg",
      "views": 997,
      "like_count": 34,
      "comment_count": 13,
      "channel_name": "D2C Diaries",
      "channel_id": "UCaB1dzAwsxDp6vWqaH7ZNLg",
      "channel_avg_views": 577.44,
      "outlier_score": 2.59,
      "recency_boost": 1.0,
      "engagement_modifiers": 1.5,
      "published_at": "2026-01-22T17:11:30Z",
      "fetched_at": "2026-02-02T19:42:43.746759+00:00",
      "source": "youtube",
      "api_source": "youtube_data_api"
    },
    {
      "id": "9K6pq2AIVyo",
      "title": "Latest TRICK to Increase Sales and Orders on Amazon Flipkart Seller Marketplace in 2026",
      "url": "https://www.youtube.com/watch?v=9K6pq2AIVyo",
      "thumbnail_url": "https://img.youtube.com/vi/9K6pq2AIVyo/hqdefault.jpg",
      "views": 4500,
      "like_count": 208,
      "comment_count": 77,
      "channel_name": "ONLINE BERI - Ecommerce Expert",
      "channel_id": "UCcTNe2yJ18egX0gAoszHsqA",
      "channel_avg_views": 2893.2,
      "outlier_score": 2.51,
      "recency_boost": 1.24,
      "engagement_modifiers": 1.3,
      "published_at": "2026-02-01T11:55:29Z",
      "fetched_at": "2026-02-02T19:42:06.360668+00:00",
      "source": "youtube",
      "api_source": "youtube_data_api"
    },
    {
      "id": "Vx1FCHbsGYY",
      "title": "This is how I hit $500/day as a 1-person Shopify store owner.",
      "url": "https://www.youtube.com/watch?v=Vx1FCHbsGYY",
      "thumbnail_url": "https://img.youtube.com/vi/Vx1FCHbsGYY/hqdefault.jpg",
      "views": 2377,
      "like_count": 184,
      "comment_count": 5,
      "channel_name": "Arie Scherson",
      "channel_id": "UCLX9HF0CKKiBSkkhqpYGxgQ",
      "channel_avg_views": 1766.08,
      "outlier_score": 2.13,
      "recency_boost": 1.22,
      "engagement_modifiers": 1.3,
      "published_at": "2026-01-31T20:22:55Z",
      "fetched_at": "2026-02-02T19:42:37.573817+00:00",
      "source": "youtube",
      "api_source": "youtube_data_api"
    },
    {
      "id": "DQAXOxURNa0",
      "title": "⭐️ TOP 10 PRODUCTS TO SELL IN FEBRUARY 2026 | DROPSHIPPING SHOPIFY",
      "url": "https://www.youtube.com/watch?v=DQAXOxURNa0",
      "thumbnail_url": "https://img.youtube.com/vi/DQAXOxURNa0/hqdefault.jpg",
      "views": 8582,
      "like_count": 576,
      "comment_count": 65,
      "channel_name": "Ac Hampton",
      "channel_id": "UC3qB4xFJkl0EYoTVbhnn0OQ",
      "channel_avg_views": 6822.42,
      "outlier_score": 2.11,
      "recency_boost": 1.12,
      "engagement_modifiers": 1.5,
      "published_at": "2026-01-29T13:00:24Z",
      "fetched_at": "2026-02-02T19:42:33.110530+00:00",
      "source": "youtube",
      "api_source": "youtube_data_api"
    }
  ]
}